hawaii_sdk/__init__.py
hawaii_sdk/communication/__init__.py
hawaii_sdk/communication/abstracts.py
hawaii_sdk/communication/command_builders.py
hawaii_sdk/communication/communicators.py
hawaii_sdk/communication/error_codes.py
hawaii_sdk/communication/mocked_communicators.py
hawaii_sdk/devices/__init__.py
hawaii_sdk/devices/device_manager.py
hawaii_sdk/devices/multi_devices/__init__.py
hawaii_sdk/devices/single_devices/__init__.py
hawaii_sdk/devices/single_devices/abstract_device.py
hawaii_sdk/devices/single_devices/monochromator.py
hawaii_sdk/utils/__init__.py
hawaii_sdk/utils/utils.py
hawaii_sdk-0.1.0.dist-info/LICENSE
hawaii_sdk-0.1.0.dist-info/METADATA
hawaii_sdk-0.1.0.dist-info/WHEEL
hawaii_sdk-0.1.0.dist-info/RECORD
